.gitignore
CHANGES.txt
COPYRIGHT.txt
LICENSE.txt
Makefile
README.txt
bootstrap.py
buildout.cfg
setup.py
ztk-versions-1.0.1.cfg
src/cipher/__init__.py
src/cipher.background.egg-info/PKG-INFO
src/cipher.background.egg-info/SOURCES.txt
src/cipher.background.egg-info/dependency_links.txt
src/cipher.background.egg-info/not-zip-safe
src/cipher.background.egg-info/requires.txt
src/cipher.background.egg-info/top_level.txt
src/cipher/background/__init__.py
src/cipher/background/contextmanagers.py
src/cipher/background/testing.py
src/cipher/background/thread.py
src/cipher/background/tests/__init__.py
src/cipher/background/tests/test_contextmanagers.py
src/cipher/background/tests/test_thread.py