Metadata-Version: 1.1
Name: cipher.background
Version: 1.0.2
Summary: Background thread support with ZODB support
Home-page: http://pypi.python.org/pypi/cipher.background/
Author: Zope Foundation and Contributors
Author-email: zope-dev@zope.org
License: ZPL 2.1
Keywords: CipherHealth background thread ZODB
Platform: UNKNOWN
Classifier: Development Status :: 4 - Beta
Classifier: Environment :: Web Environment
Classifier: Intended Audience :: Developers
Classifier: Programming Language :: Python
Classifier: Natural Language :: English
Classifier: Operating System :: OS Independent
Classifier: Topic :: Internet :: WWW/HTTP
Classifier: Framework :: Zope3
